{
    "id": 11,
    "release-date": "25 Mayıs 2016",
    "synopsis": "34 yaşında, işsiz bir bakire olan NEET, evinden atılır, parasız kalır ve hayatının tamamen çıkmaza girdiğini fark eder. Kendine acıdığı sırada bir kamyon tarafından ezilir ve sersem bir şekilde ölür. Sonra kılıçların ve büyünün olduğu farklı bir dünyada uyanır!\n\r &nbsp; \n\rBir bebek olan Rudeus olarak yeniden doğar ve “Bu sefer, gerçekten hayatımı yaşayacağım. …!” diye düşünür ve pişmanlık duymadan bir hayat yaşamaya karar verir.\n\r &nbsp; \n\rÖnceki hayatının zekasını kullanarak, Rudeus hızla büyü yeteneği geliştirir ve küçük bir kız tarafından eğitilir. Ayrıca zümrüt yeşili saçlı güzel bir çeyrek elfle tanışır. Yeni hayatı açılmaya başlar.",
    "status": "Çeviriliyor",
    "image": "http://lastfansub.repl.co/covers/mushoku-tensei/11.webp"
}